{
  "credit": "Made with Blockbench",
  "texture_size": [
    128,
    128
  ],
  "elements": [
    {
      "from": [
        7,
        -16,
        7
      ],
      "to": [
        9,
        32,
        9
      ],
      "faces": {
        "north": {
          "uv": [
            0,
            3.125,
            0.25,
            9.125
          ],
          "texture": "#1"
        },
        "east": {
          "uv": [
            0.25,
            3.125,
            0.5,
            9.125
          ],
          "texture": "#1"
        },
        "south": {
          "uv": [
            0.5,
            3.125,
            0.75,
            9.125
          ],
          "texture": "#1"
        },
        "west": {
          "uv": [
            0.75,
            3.125,
            1,
            9.125
          ],
          "texture": "#1"
        },
        "up": {
          "uv": [
            4.375,
            2.875,
            4.125,
            2.625
          ],
          "texture": "#1"
        },
        "down": {
          "uv": [
            1.5,
            4.25,
            1.25,
            4.5
          ],
          "texture": "#1"
        }
      }
    },
    {
      "from": [
        7,
        28,
        -11
      ],
      "to": [
        9,
        30,
        12
      ],
      "faces": {
        "north": {
          "uv": [
            1.5,
            4.25,
            1.75,
            4.5
          ],
          "texture": "#1"
        },
        "east": {
          "uv": [
            1,
            3.125,
            3.875,
            3.375
          ],
          "texture": "#1"
        },
        "south": {
          "uv": [
            1.75,
            4.25,
            2,
            4.5
          ],
          "texture": "#1"
        },
        "west": {
          "uv": [
            1,
            3.375,
            3.875,
            3.625
          ],
          "texture": "#1"
        },
        "up": {
          "uv": [
            3.75,
            2.875,
            3.5,
            0
          ],
          "texture": "#1"
        },
        "down": {
          "uv": [
            1.25,
            3.625,
            1,
            6.5
          ],
          "texture": "#1"
        }
      }
    },
    {
      "from": [
        7,
        23,
        8.5
      ],
      "to": [
        9,
        25,
        15.5
      ],
      "rotation": {
        "angle": 45,
        "axis": "x",
        "origin": [
          8,
          24,
          9.5
        ]
      },
      "faces": {
        "north": {
          "uv": [
            2.625,
            4.25,
            2.875,
            4.5
          ],
          "texture": "#1"
        },
        "east": {
          "uv": [
            3.5,
            2.875,
            4.375,
            3.125
          ],
          "texture": "#1"
        },
        "south": {
          "uv": [
            2.875,
            4.25,
            3.125,
            4.5
          ],
          "texture": "#1"
        },
        "west": {
          "uv": [
            1.25,
            3.625,
            2.125,
            3.875
          ],
          "texture": "#1"
        },
        "up": {
          "uv": [
            2.375,
            4.5,
            2.125,
            3.625
          ],
          "texture": "#1"
        },
        "down": {
          "uv": [
            2.625,
            3.625,
            2.375,
            4.5
          ],
          "texture": "#1"
        }
      }
    },
    {
      "from": [
        7,
        6,
        8.5
      ],
      "to": [
        9,
        8,
        15.5
      ],
      "rotation": {
        "angle": -45,
        "axis": "x",
        "origin": [
          8,
          7,
          9.5
        ]
      },
      "faces": {
        "north": {
          "uv": [
            2.625,
            4.25,
            2.875,
            4.5
          ],
          "texture": "#1"
        },
        "east": {
          "uv": [
            3.5,
            2.875,
            4.375,
            3.125
          ],
          "texture": "#1"
        },
        "south": {
          "uv": [
            2.875,
            4.25,
            3.125,
            4.5
          ],
          "texture": "#1"
        },
        "west": {
          "uv": [
            1.25,
            3.625,
            2.125,
            3.875
          ],
          "texture": "#1"
        },
        "up": {
          "uv": [
            2.375,
            4.5,
            2.125,
            3.625
          ],
          "texture": "#1"
        },
        "down": {
          "uv": [
            2.625,
            3.625,
            2.375,
            4.5
          ],
          "texture": "#1"
        }
      }
    },
    {
      "from": [
        8,
        3,
        -7
      ],
      "to": [
        8,
        28,
        7
      ],
      "faces": {
        "north": {
          "uv": [
            0,
            0,
            0,
            3.125
          ],
          "texture": "#1"
        },
        "east": {
          "uv": [
            0,
            0,
            1.75,
            3.125
          ],
          "texture": "#1"
        },
        "south": {
          "uv": [
            0,
            0,
            0,
            3.125
          ],
          "texture": "#1"
        },
        "west": {
          "uv": [
            1.75,
            0,
            3.5,
            3.125
          ],
          "texture": "#1"
        },
        "up": {
          "uv": [
            0,
            1.75,
            0,
            0
          ],
          "texture": "#1"
        },
        "down": {
          "uv": [
            0,
            0,
            0,
            1.75
          ],
          "texture": "#1"
        }
      }
    },
    {
      "from": [
        6.5,
        5.5,
        6.5
      ],
      "to": [
        9.5,
        8.5,
        9.5
      ],
      "rotation": {
        "angle": 0,
        "axis": "y",
        "origin": [
          0,
          -17,
          0
        ]
      },
      "faces": {
        "north": {
          "uv": [
            3,
            3.875,
            3.375,
            4.25
          ],
          "texture": "#1"
        },
        "east": {
          "uv": [
            3.875,
            3.125,
            4.25,
            3.5
          ],
          "texture": "#1"
        },
        "south": {
          "uv": [
            3.375,
            3.875,
            3.75,
            4.25
          ],
          "texture": "#1"
        },
        "west": {
          "uv": [
            3.75,
            3.875,
            4.125,
            4.25
          ],
          "texture": "#1"
        },
        "up": {
          "uv": [
            4.375,
            0.375,
            4,
            0
          ],
          "texture": "#1"
        },
        "down": {
          "uv": [
            4.375,
            0.375,
            4,
            0.75
          ],
          "texture": "#1"
        }
      }
    },
    {
      "from": [
        6.5,
        22.5,
        6.5
      ],
      "to": [
        9.5,
        25.5,
        9.5
      ],
      "rotation": {
        "angle": 0,
        "axis": "y",
        "origin": [
          0,
          -17,
          0
        ]
      },
      "faces": {
        "north": {
          "uv": [
            3,
            3.875,
            3.375,
            4.25
          ],
          "texture": "#1"
        },
        "east": {
          "uv": [
            3.875,
            3.125,
            4.25,
            3.5
          ],
          "texture": "#1"
        },
        "south": {
          "uv": [
            3.375,
            3.875,
            3.75,
            4.25
          ],
          "texture": "#1"
        },
        "west": {
          "uv": [
            3.75,
            3.875,
            4.125,
            4.25
          ],
          "texture": "#1"
        },
        "up": {
          "uv": [
            4.375,
            0.375,
            4,
            0
          ],
          "texture": "#1"
        },
        "down": {
          "uv": [
            4.375,
            0.375,
            4,
            0.75
          ],
          "texture": "#1"
        }
      }
    },
    {
      "from": [
        6.5,
        27.5,
        6.5
      ],
      "to": [
        9.5,
        30.5,
        9.5
      ],
      "rotation": {
        "angle": 0,
        "axis": "y",
        "origin": [
          0,
          -17,
          0
        ]
      },
      "faces": {
        "north": {
          "uv": [
            3,
            3.875,
            3.375,
            4.25
          ],
          "texture": "#1"
        },
        "east": {
          "uv": [
            3.875,
            3.125,
            4.25,
            3.5
          ],
          "texture": "#1"
        },
        "south": {
          "uv": [
            3.375,
            3.875,
            3.75,
            4.25
          ],
          "texture": "#1"
        },
        "west": {
          "uv": [
            3.75,
            3.875,
            4.125,
            4.25
          ],
          "texture": "#1"
        },
        "up": {
          "uv": [
            4.375,
            0.375,
            4,
            0
          ],
          "texture": "#1"
        },
        "down": {
          "uv": [
            4.375,
            0.375,
            4,
            0.75
          ],
          "texture": "#1"
        }
      }
    }
  ],
  "display": {
    "thirdperson_righthand": {
      "rotation": [
        39.5,
        0,
        0
      ],
      "translation": [
        0,
        8,
        7.5
      ]
    },
    "thirdperson_lefthand": {
      "rotation": [
        39.5,
        0,
        0
      ],
      "translation": [
        0,
        8,
        7.5
      ]
    },
    "firstperson_righthand": {
      "rotation": [
        -26.25,
        15,
        0
      ],
      "translation": [
        11,
        8.5,
        -8.5
      ]
    },
    "firstperson_lefthand": {
      "rotation": [
        -26.25,
        15,
        0
      ],
      "translation": [
        11,
        8.5,
        -8.5
      ]
    },
    "ground": {
      "rotation": [
        0,
        0,
        90
      ],
      "translation": [
        0,
        -2,
        0
      ],
      "scale": [
        0.22,
        0.22,
        0.22
      ]
    },
    "gui": {
      "rotation": [
        -14.57,
        46.59,
        37.5
      ],
      "translation": [
        1.25,
        0,
        0
      ],
      "scale": [
        0.37,
        0.37,
        0.37
      ]
    },
    "head": {
      "translation": [
        0,
        28.75,
        7.5
      ],
      "scale": [
        1.47,
        1.47,
        1.47
      ]
    },
    "fixed": {
      "rotation": [
        -90,
        45,
        90
      ],
      "translation": [
        1.25,
        0,
        0
      ],
      "scale": [
        0.34,
        0.34,
        0.34
      ]
    }
  },
  "groups": [
    {
      "name": "group",
      "origin": [
        8,
        8,
        8
      ],
      "color": 0,
      "children": [
        0,
        1,
        2,
        3,
        4,
        5,
        6,
        7
      ]
    }
  ]
}