{
  "type": "minecraft:crafting_shaped",
  "pattern": [
    "012",
    "345",
    "678"
  ],
  "key": {
    "0": {
      "item": "minecraft:iron_ingot"
    },
    "1": {
      "item": "minecraft:yellow_dye"
    },
    "2": {
      "item": "minecraft:iron_ingot"
    },
    "3": {
      "item": "minecraft:dried_kelp"
    },
    "4": {
      "item": "minecraft:glass"
    },
    "5": {
      "item": "minecraft:dried_kelp"
    },
    "6": {
      "tag": "minecraft:coals"
    },
    "7": {
      "item": "minecraft:hopper"
    },
    "8": {
      "tag": "minecraft:coals"
    }
  },
  "result": {
    "item": "jigsaw:hazmat_helmet",
    "count": 1
  }
}